.gitignore
CHANGES
MANIFEST.in
PKG-INFO
README.rst
buildout.cfg
setup.cfg
setup.py
zkaffold/__init__.py
zkaffold/build_site.py
zkaffold/config.py
zkaffold/consolehelpers.py
zkaffold/contentexporter.py
zkaffold/contentimporter.py
zkaffold/main.py
zkaffold/memberimporter.py
zkaffold/setuphandlers.py
zkaffold/wordy.py
zkaffold.egg-info/PKG-INFO
zkaffold.egg-info/SOURCES.txt
zkaffold.egg-info/dependency_links.txt
zkaffold.egg-info/entry_points.txt
zkaffold.egg-info/requires.txt
zkaffold.egg-info/top_level.txt
zkaffold/exportimport/__init__.py
zkaffold/exportimport/tests/__init__.py
zkaffold/exportimport/tests/test_exportimport.py
zkaffold/tests/__init__.py
zkaffold/tests/functional.py
zkaffold/tests/test_contentexporter.py
zkaffold/tests/test_contentimporter.py