Metadata-Version: 1.0
Name: zkaffold
Version: 0.0.11
Summary: Build out demonstration content for plone
Home-page: http://pypi.python.org/pypi/zkaffold
Author: Pat Smith
Author-email: pat.smith@isotoma.com
License: UNKNOWN
Platform: UNKNOWN
